PasteBinAPIWrapper/__init__.py
PasteBinAPIWrapper/apiWrapper.py
PasteBinAPIWrapper-0.0.1.dist-info/LICENSE.txt
PasteBinAPIWrapper-0.0.1.dist-info/METADATA
PasteBinAPIWrapper-0.0.1.dist-info/WHEEL
PasteBinAPIWrapper-0.0.1.dist-info/top_level.txt
PasteBinAPIWrapper-0.0.1.dist-info/RECORD
