Metadata-Version: 2.1
Name: PasteBinAPIWrapper
Version: 0.0.1
Requires-Python: >=3.5
License-File: LICENSE.txt
Requires-Dist: requests
